{"pageProps":{"initialApolloState":{"Product:35":{"id":35,"title":"Advent Laptop Bag","slug":"advent-laptop-bag","unit":"1 pc(s)","price":200,"salePrice":160,"description":"Material: Laptop Shoulder Bag is made of quality canvas, protecting your laptop from dust, scratches and water","discountInPercent":20,"type":"BAGS","image":"https://s3.amazonaws.com/redqteam.com/pickbazar/Advent_laptop_bags.jpg","author":null,"gallery":[{"type":"id","generated":true,"id":"Product:35.gallery.0","typename":"Gallery"},{"type":"id","generated":true,"id":"Product:35.gallery.1","typename":"Gallery"},{"type":"id","generated":true,"id":"Product:35.gallery.2","typename":"Gallery"},{"type":"id","generated":true,"id":"Product:35.gallery.3","typename":"Gallery"}],"categories":[{"type":"id","generated":false,"id":"Category:18","typename":"Category"}],"__typename":"Product"},"Product:35.gallery.0":{"url":"https://s3.amazonaws.com/redqteam.com/pickbazar/Advent_laptop_bags.jpg","__typename":"Gallery"},"Product:35.gallery.1":{"url":"https://s3.amazonaws.com/redqteam.com/pickbazar/Advent_laptop_bags.jpg","__typename":"Gallery"},"Product:35.gallery.2":{"url":"https://s3.amazonaws.com/redqteam.com/pickbazar/Advent_laptop_bags.jpg","__typename":"Gallery"},"Product:35.gallery.3":{"url":"https://s3.amazonaws.com/redqteam.com/pickbazar/Advent_laptop_bags.jpg","__typename":"Gallery"},"Category:18":{"id":18,"title":"Laptop bags","slug":"laptop-bags","__typename":"Category","icon":"LaptopBags","children":[]},"Product:36":{"id":36,"title":"Alex Maqueeen Shoulder Bag","slug":"alex-maqueen-shoulder-bag","unit":"1 pc(s)","price":250,"salePrice":200,"description":"Luxury British fashion house Alexander McQueen is famed for its exquisitely designed handbags and accessories, as showcased through this stunning black Box bag. Expertly crafted in Italy from supple calf leather, the bag is an ideal accessory choice which suits a variety of styles and occasions.","discountInPercent":20,"type":"BAGS","image":"https://s3.amazonaws.com/redqteam.com/pickbazar/Alex_maquine_shoulder.jpg","author":null,"gallery":[{"type":"id","generated":true,"id":"Product:36.gallery.0","typename":"Gallery"},{"type":"id","generated":true,"id":"Product:36.gallery.1","typename":"Gallery"},{"type":"id","generated":true,"id":"Product:36.gallery.2","typename":"Gallery"},{"type":"id","generated":true,"id":"Product:36.gallery.3","typename":"Gallery"}],"categories":[{"type":"id","generated":false,"id":"Category:16","typename":"Category"}],"__typename":"Product"},"Product:36.gallery.0":{"url":"https://s3.amazonaws.com/redqteam.com/pickbazar/Alex_maquine_shoulder.jpg","__typename":"Gallery"},"Product:36.gallery.1":{"url":"https://s3.amazonaws.com/redqteam.com/pickbazar/Alex_maquine_shoulder.jpg","__typename":"Gallery"},"Product:36.gallery.2":{"url":"https://s3.amazonaws.com/redqteam.com/pickbazar/Alex_maquine_shoulder.jpg","__typename":"Gallery"},"Product:36.gallery.3":{"url":"https://s3.amazonaws.com/redqteam.com/pickbazar/Alex_maquine_shoulder.jpg","__typename":"Gallery"},"Category:16":{"id":16,"title":"Shoulder bags","slug":"shoulder-bags","__typename":"Category","icon":"ShoulderBags","children":[]},"Product:37":{"id":37,"title":"Armani Black Wallet","slug":"armani-black-wallet","unit":"1 pc(s)","price":150,"salePrice":135,"description":"Brand New Emporio Armani Leather Wallet. Shipped with USPS First Class Package.","discountInPercent":10,"type":"BAGS","image":"https://s3.amazonaws.com/redqteam.com/pickbazar/Armani_black_wallet.jpg","author":null,"gallery":[{"type":"id","generated":true,"id":"Product:37.gallery.0","typename":"Gallery"},{"type":"id","generated":true,"id":"Product:37.gallery.1","typename":"Gallery"},{"type":"id","generated":true,"id":"Product:37.gallery.2","typename":"Gallery"},{"type":"id","generated":true,"id":"Product:37.gallery.3","typename":"Gallery"}],"categories":[{"type":"id","generated":false,"id":"Category:17","typename":"Category"}],"__typename":"Product"},"Product:37.gallery.0":{"url":"https://s3.amazonaws.com/redqteam.com/pickbazar/Armani_black_wallet.jpg","__typename":"Gallery"},"Product:37.gallery.1":{"url":"https://s3.amazonaws.com/redqteam.com/pickbazar/Armani_black_wallet.jpg","__typename":"Gallery"},"Product:37.gallery.2":{"url":"https://s3.amazonaws.com/redqteam.com/pickbazar/Armani_black_wallet.jpg","__typename":"Gallery"},"Product:37.gallery.3":{"url":"https://s3.amazonaws.com/redqteam.com/pickbazar/Armani_black_wallet.jpg","__typename":"Gallery"},"Category:17":{"id":17,"title":"Wallet","slug":"wallet","__typename":"Category","icon":"Wallet","children":[]},"Product:38":{"id":38,"title":"Armani Handbag","slug":"armani-handbag","unit":"1 pc(s)","price":350,"salePrice":0,"description":"Black logo embossed messenger bag from Giorgio Armani featuring an adjustable shoulder strap, a top zip fastening and a front zip pocket.","discountInPercent":0,"type":"BAGS","image":"https://s3.amazonaws.com/redqteam.com/pickbazar/Armani_Handbag.jpg","author":null,"gallery":[{"type":"id","generated":true,"id":"Product:38.gallery.0","typename":"Gallery"},{"type":"id","generated":true,"id":"Product:38.gallery.1","typename":"Gallery"},{"type":"id","generated":true,"id":"Product:38.gallery.2","typename":"Gallery"},{"type":"id","generated":true,"id":"Product:38.gallery.3","typename":"Gallery"}],"categories":[{"type":"id","generated":false,"id":"Category:15","typename":"Category"}],"__typename":"Product"},"Product:38.gallery.0":{"url":"https://s3.amazonaws.com/redqteam.com/pickbazar/Armani_Handbag.jpg","__typename":"Gallery"},"Product:38.gallery.1":{"url":"https://s3.amazonaws.com/redqteam.com/pickbazar/Armani_Handbag.jpg","__typename":"Gallery"},"Product:38.gallery.2":{"url":"https://s3.amazonaws.com/redqteam.com/pickbazar/Armani_Handbag.jpg","__typename":"Gallery"},"Product:38.gallery.3":{"url":"https://s3.amazonaws.com/redqteam.com/pickbazar/Armani_Handbag.jpg","__typename":"Gallery"},"Category:15":{"id":15,"title":"Hand bags","slug":"hand-bags","__typename":"Category","icon":"HandBags","children":[]},"Product:39":{"id":39,"title":"Armani Leather Purse","slug":"armani-leather-purse","unit":"1 pc(s)","price":50,"salePrice":40,"description":"The name Giorgio Armani has become synonymous with clean lines and Italian style. One of the most recognisable fashion houses in the world, the label has dressed some of the world’s most beautiful women.","discountInPercent":20,"type":"BAGS","image":"https://s3.amazonaws.com/redqteam.com/pickbazar/Armani_leather_purse.jpg","author":null,"gallery":[{"type":"id","generated":true,"id":"Product:39.gallery.0","typename":"Gallery"},{"type":"id","generated":true,"id":"Product:39.gallery.1","typename":"Gallery"},{"type":"id","generated":true,"id":"Product:39.gallery.2","typename":"Gallery"},{"type":"id","generated":true,"id":"Product:39.gallery.3","typename":"Gallery"}],"categories":[{"type":"id","generated":false,"id":"Category:14","typename":"Category"}],"__typename":"Product"},"Product:39.gallery.0":{"url":"https://s3.amazonaws.com/redqteam.com/pickbazar/Armani_leather_purse.jpg","__typename":"Gallery"},"Product:39.gallery.1":{"url":"https://s3.amazonaws.com/redqteam.com/pickbazar/Armani_leather_purse.jpg","__typename":"Gallery"},"Product:39.gallery.2":{"url":"https://s3.amazonaws.com/redqteam.com/pickbazar/Armani_leather_purse.jpg","__typename":"Gallery"},"Product:39.gallery.3":{"url":"https://s3.amazonaws.com/redqteam.com/pickbazar/Armani_leather_purse.jpg","__typename":"Gallery"},"Category:14":{"id":14,"title":"Purse","slug":"purse","__typename":"Category","icon":"Purse","children":[]},"Product:40":{"id":40,"title":"Armani Purse","slug":"armani-purse","unit":"1 pc(s)","price":80,"salePrice":72,"description":"Black logo embossed messenger bag from Giorgio Armani featuring an adjustable shoulder strap, a top zip fastening and a front zip pocket.","discountInPercent":10,"type":"BAGS","image":"https://s3.amazonaws.com/redqteam.com/pickbazar/Armani_purse.jpg","author":null,"gallery":[{"type":"id","generated":true,"id":"Product:40.gallery.0","typename":"Gallery"},{"type":"id","generated":true,"id":"Product:40.gallery.1","typename":"Gallery"},{"type":"id","generated":true,"id":"Product:40.gallery.2","typename":"Gallery"},{"type":"id","generated":true,"id":"Product:40.gallery.3","typename":"Gallery"}],"categories":[{"type":"id","generated":false,"id":"Category:14","typename":"Category"}],"__typename":"Product"},"Product:40.gallery.0":{"url":"https://s3.amazonaws.com/redqteam.com/pickbazar/Armani_purse.jpg","__typename":"Gallery"},"Product:40.gallery.1":{"url":"https://s3.amazonaws.com/redqteam.com/pickbazar/Armani_purse.jpg","__typename":"Gallery"},"Product:40.gallery.2":{"url":"https://s3.amazonaws.com/redqteam.com/pickbazar/Armani_purse.jpg","__typename":"Gallery"},"Product:40.gallery.3":{"url":"https://s3.amazonaws.com/redqteam.com/pickbazar/Armani_purse.jpg","__typename":"Gallery"},"Product:41":{"id":41,"title":"Armani Wallet","slug":"armani-wallet","unit":"1 pc(s)","price":60,"salePrice":0,"description":"Brand New Emporio Armani Leather Wallet. Shipped with USPS First Class Package.","discountInPercent":0,"type":"BAGS","image":"https://s3.amazonaws.com/redqteam.com/pickbazar/Armani_wallet.jpg","author":null,"gallery":[{"type":"id","generated":true,"id":"Product:41.gallery.0","typename":"Gallery"},{"type":"id","generated":true,"id":"Product:41.gallery.1","typename":"Gallery"},{"type":"id","generated":true,"id":"Product:41.gallery.2","typename":"Gallery"},{"type":"id","generated":true,"id":"Product:41.gallery.3","typename":"Gallery"}],"categories":[{"type":"id","generated":false,"id":"Category:17","typename":"Category"}],"__typename":"Product"},"Product:41.gallery.0":{"url":"https://s3.amazonaws.com/redqteam.com/pickbazar/Armani_wallet.jpg","__typename":"Gallery"},"Product:41.gallery.1":{"url":"https://s3.amazonaws.com/redqteam.com/pickbazar/Armani_wallet.jpg","__typename":"Gallery"},"Product:41.gallery.2":{"url":"https://s3.amazonaws.com/redqteam.com/pickbazar/Armani_wallet.jpg","__typename":"Gallery"},"Product:41.gallery.3":{"url":"https://s3.amazonaws.com/redqteam.com/pickbazar/Armani_wallet.jpg","__typename":"Gallery"},"Product:42":{"id":42,"title":"Chanel Shoulder Bag","slug":"chanel-shoulder-bag","unit":"1 pc(s)","price":190,"salePrice":171,"description":"00% Authenticity Guaranteed Chanel Classic Jumbo Single Flap Black Caviar Shoulder Bag","discountInPercent":10,"type":"BAGS","image":"https://s3.amazonaws.com/redqteam.com/pickbazar/chanel_shoulder_bag.jpg","author":null,"gallery":[{"type":"id","generated":true,"id":"Product:42.gallery.0","typename":"Gallery"},{"type":"id","generated":true,"id":"Product:42.gallery.1","typename":"Gallery"},{"type":"id","generated":true,"id":"Product:42.gallery.2","typename":"Gallery"},{"type":"id","generated":true,"id":"Product:42.gallery.3","typename":"Gallery"}],"categories":[{"type":"id","generated":false,"id":"Category:16","typename":"Category"}],"__typename":"Product"},"Product:42.gallery.0":{"url":"https://s3.amazonaws.com/redqteam.com/pickbazar/chanel_shoulder_bag.jpg","__typename":"Gallery"},"Product:42.gallery.1":{"url":"https://s3.amazonaws.com/redqteam.com/pickbazar/chanel_shoulder_bag.jpg","__typename":"Gallery"},"Product:42.gallery.2":{"url":"https://s3.amazonaws.com/redqteam.com/pickbazar/chanel_shoulder_bag.jpg","__typename":"Gallery"},"Product:42.gallery.3":{"url":"https://s3.amazonaws.com/redqteam.com/pickbazar/chanel_shoulder_bag.jpg","__typename":"Gallery"},"Product:43":{"id":43,"title":"Chanel Wallet Brown","slug":"chanel-wallet-brown","unit":"1 pc(s)","price":90,"salePrice":0,"description":"Beautiful new Chanel fingerless wallet. Tweed with leather CC on top and leather on the backside of the wallet.","discountInPercent":0,"type":"BAGS","image":"https://s3.amazonaws.com/redqteam.com/pickbazar/chanel_wallet_brown.jpg","author":null,"gallery":[{"type":"id","generated":true,"id":"Product:43.gallery.0","typename":"Gallery"},{"type":"id","generated":true,"id":"Product:43.gallery.1","typename":"Gallery"},{"type":"id","generated":true,"id":"Product:43.gallery.2","typename":"Gallery"},{"type":"id","generated":true,"id":"Product:43.gallery.3","typename":"Gallery"}],"categories":[{"type":"id","generated":false,"id":"Category:17","typename":"Category"}],"__typename":"Product"},"Product:43.gallery.0":{"url":"https://s3.amazonaws.com/redqteam.com/pickbazar/chanel_wallet_brown.jpg","__typename":"Gallery"},"Product:43.gallery.1":{"url":"https://s3.amazonaws.com/redqteam.com/pickbazar/chanel_wallet_brown.jpg","__typename":"Gallery"},"Product:43.gallery.2":{"url":"https://s3.amazonaws.com/redqteam.com/pickbazar/chanel_wallet_brown.jpg","__typename":"Gallery"},"Product:43.gallery.3":{"url":"https://s3.amazonaws.com/redqteam.com/pickbazar/chanel_wallet_brown.jpg","__typename":"Gallery"},"Product:44":{"id":44,"title":"Chanel Wallet","slug":"chanel-wallet","unit":"1 pc(s)","price":60,"salePrice":48,"description":"Beautiful new Chanel fingerless wallet. Tweed with leather CC on top and leather on the backside of the wallet.","discountInPercent":20,"type":"BAGS","image":"https://s3.amazonaws.com/redqteam.com/pickbazar/Chanel_wallet.jpg","author":null,"gallery":[{"type":"id","generated":true,"id":"Product:44.gallery.0","typename":"Gallery"},{"type":"id","generated":true,"id":"Product:44.gallery.1","typename":"Gallery"},{"type":"id","generated":true,"id":"Product:44.gallery.2","typename":"Gallery"},{"type":"id","generated":true,"id":"Product:44.gallery.3","typename":"Gallery"}],"categories":[{"type":"id","generated":false,"id":"Category:17","typename":"Category"}],"__typename":"Product"},"Product:44.gallery.0":{"url":"https://s3.amazonaws.com/redqteam.com/pickbazar/Chanel_wallet.jpg","__typename":"Gallery"},"Product:44.gallery.1":{"url":"https://s3.amazonaws.com/redqteam.com/pickbazar/Chanel_wallet.jpg","__typename":"Gallery"},"Product:44.gallery.2":{"url":"https://s3.amazonaws.com/redqteam.com/pickbazar/Chanel_wallet.jpg","__typename":"Gallery"},"Product:44.gallery.3":{"url":"https://s3.amazonaws.com/redqteam.com/pickbazar/Chanel_wallet.jpg","__typename":"Gallery"},"Product:45":{"id":45,"title":"Givenchy Shoulder Bag","slug":"givenchy-shoulder-bag","unit":"1 pc(s)","price":210,"salePrice":0,"description":"Established in 1952, Givenchy's stance on contemporary elegance is perfectly captured through the brand’s premium accessory collections. Crafted from calf leather, this grey GV3 croc-effect shoulder bag from Givenchy features a chain top handle with logo charm, a detachable shoulder strap, a front flap closure, a metal logo plaque to the front, gold-tone hardware and suede panels.","discountInPercent":0,"type":"BAGS","image":"https://s3.amazonaws.com/redqteam.com/pickbazar/Givenchy_shoulder_bag.jpg","author":null,"gallery":[{"type":"id","generated":true,"id":"Product:45.gallery.0","typename":"Gallery"},{"type":"id","generated":true,"id":"Product:45.gallery.1","typename":"Gallery"},{"type":"id","generated":true,"id":"Product:45.gallery.2","typename":"Gallery"},{"type":"id","generated":true,"id":"Product:45.gallery.3","typename":"Gallery"}],"categories":[{"type":"id","generated":false,"id":"Category:16","typename":"Category"}],"__typename":"Product"},"Product:45.gallery.0":{"url":"https://s3.amazonaws.com/redqteam.com/pickbazar/Chanel_wallet.jpg","__typename":"Gallery"},"Product:45.gallery.1":{"url":"https://s3.amazonaws.com/redqteam.com/pickbazar/Chanel_wallet.jpg","__typename":"Gallery"},"Product:45.gallery.2":{"url":"https://s3.amazonaws.com/redqteam.com/pickbazar/Chanel_wallet.jpg","__typename":"Gallery"},"Product:45.gallery.3":{"url":"https://s3.amazonaws.com/redqteam.com/pickbazar/Chanel_wallet.jpg","__typename":"Gallery"},"Product:46":{"id":46,"title":"Givenchy Purse","slug":"givenchy-purse","unit":"1 pc(s)","price":75,"salePrice":60,"description":"Established in 1952, Givenchy's stance on contemporary elegance is perfectly captured through the brand’s premium accessory collections. Crafted from calf leather, this grey GV3 croc-effect shoulder bag from Givenchy features a chain top handle with logo charm, a detachable shoulder strap, a front flap closure, a metal logo plaque to the front, gold-tone hardware and suede panels.","discountInPercent":20,"type":"BAGS","image":"https://s3.amazonaws.com/redqteam.com/pickbazar/givency_purse.jpg","author":null,"gallery":[{"type":"id","generated":true,"id":"Product:46.gallery.0","typename":"Gallery"},{"type":"id","generated":true,"id":"Product:46.gallery.1","typename":"Gallery"},{"type":"id","generated":true,"id":"Product:46.gallery.2","typename":"Gallery"},{"type":"id","generated":true,"id":"Product:46.gallery.3","typename":"Gallery"}],"categories":[{"type":"id","generated":false,"id":"Category:14","typename":"Category"}],"__typename":"Product"},"Product:46.gallery.0":{"url":"https://s3.amazonaws.com/redqteam.com/pickbazar/givency_purse.jpg","__typename":"Gallery"},"Product:46.gallery.1":{"url":"https://s3.amazonaws.com/redqteam.com/pickbazar/givency_purse.jpg","__typename":"Gallery"},"Product:46.gallery.2":{"url":"https://s3.amazonaws.com/redqteam.com/pickbazar/givency_purse.jpg","__typename":"Gallery"},"Product:46.gallery.3":{"url":"https://s3.amazonaws.com/redqteam.com/pickbazar/givency_purse.jpg","__typename":"Gallery"},"Product:47":{"id":47,"title":"Gucci Handbag","slug":"gucci-handbag","unit":"1 pc(s)","price":380,"salePrice":0,"description":"Luxury Italian fashion house Gucci is renowned for its instantly recognisable bags and accessories, infusing its unique sense of quality and exquisite design into each piece. This pink logo print leather backpack from Gucci features top handles, a drawstring fastening, a pebbled leather texture, a removable zipped pouch and a vintage Gucci logo.","discountInPercent":0,"type":"BAGS","image":"https://s3.amazonaws.com/redqteam.com/pickbazar/gucchi.jpg","author":null,"gallery":[{"type":"id","generated":true,"id":"Product:47.gallery.0","typename":"Gallery"},{"type":"id","generated":true,"id":"Product:47.gallery.1","typename":"Gallery"},{"type":"id","generated":true,"id":"Product:47.gallery.2","typename":"Gallery"},{"type":"id","generated":true,"id":"Product:47.gallery.3","typename":"Gallery"}],"categories":[{"type":"id","generated":false,"id":"Category:15","typename":"Category"}],"__typename":"Product"},"Product:47.gallery.0":{"url":"https://s3.amazonaws.com/redqteam.com/pickbazar/gucchi.jpg","__typename":"Gallery"},"Product:47.gallery.1":{"url":"https://s3.amazonaws.com/redqteam.com/pickbazar/gucchi.jpg","__typename":"Gallery"},"Product:47.gallery.2":{"url":"https://s3.amazonaws.com/redqteam.com/pickbazar/gucchi.jpg","__typename":"Gallery"},"Product:47.gallery.3":{"url":"https://s3.amazonaws.com/redqteam.com/pickbazar/gucchi.jpg","__typename":"Gallery"},"Product:48":{"id":48,"title":"Givenchy Mini Purse","slug":"givenchy-mini-purse","unit":"1 pc(s)","price":65,"salePrice":52,"description":"Luxury Italian fashion house Gucci is renowned for its instantly recognisable bags and accessories, infusing its unique sense of quality and exquisite design into each piece. This pink logo print leather backpack from Gucci features top handles, a drawstring fastening, a pebbled leather texture, a removable zipped pouch and a vintage Gucci logo.","discountInPercent":20,"type":"BAGS","image":"https://s3.amazonaws.com/redqteam.com/pickbazar/gucci_mini_purse.jpg","author":null,"gallery":[{"type":"id","generated":true,"id":"Product:48.gallery.0","typename":"Gallery"},{"type":"id","generated":true,"id":"Product:48.gallery.1","typename":"Gallery"},{"type":"id","generated":true,"id":"Product:48.gallery.2","typename":"Gallery"},{"type":"id","generated":true,"id":"Product:48.gallery.3","typename":"Gallery"}],"categories":[{"type":"id","generated":false,"id":"Category:14","typename":"Category"}],"__typename":"Product"},"Product:48.gallery.0":{"url":"https://s3.amazonaws.com/redqteam.com/pickbazar/gucci_mini_purse.jpg","__typename":"Gallery"},"Product:48.gallery.1":{"url":"https://s3.amazonaws.com/redqteam.com/pickbazar/gucci_mini_purse.jpg","__typename":"Gallery"},"Product:48.gallery.2":{"url":"https://s3.amazonaws.com/redqteam.com/pickbazar/gucci_mini_purse.jpg","__typename":"Gallery"},"Product:48.gallery.3":{"url":"https://s3.amazonaws.com/redqteam.com/pickbazar/gucci_mini_purse.jpg","__typename":"Gallery"},"Product:49":{"id":49,"title":"Gucci Purse","slug":"gucci-purse","unit":"1 pc(s)","price":95,"salePrice":76,"description":"Luxury Italian fashion house Gucci is renowned for its instantly recognisable bags and accessories, infusing its unique sense of quality and exquisite design into each piece. This pink logo print leather backpack from Gucci features top handles, a drawstring fastening, a pebbled leather texture, a removable zipped pouch and a vintage Gucci logo.","discountInPercent":20,"type":"BAGS","image":"https://s3.amazonaws.com/redqteam.com/pickbazar/gucci_purse.jpg","author":null,"gallery":[{"type":"id","generated":true,"id":"Product:49.gallery.0","typename":"Gallery"},{"type":"id","generated":true,"id":"Product:49.gallery.1","typename":"Gallery"},{"type":"id","generated":true,"id":"Product:49.gallery.2","typename":"Gallery"},{"type":"id","generated":true,"id":"Product:49.gallery.3","typename":"Gallery"}],"categories":[{"type":"id","generated":false,"id":"Category:14","typename":"Category"}],"__typename":"Product"},"Product:49.gallery.0":{"url":"https://s3.amazonaws.com/redqteam.com/pickbazar/gucci_mini_purse.jpg","__typename":"Gallery"},"Product:49.gallery.1":{"url":"https://s3.amazonaws.com/redqteam.com/pickbazar/gucci_mini_purse.jpg","__typename":"Gallery"},"Product:49.gallery.2":{"url":"https://s3.amazonaws.com/redqteam.com/pickbazar/gucci_mini_purse.jpg","__typename":"Gallery"},"Product:49.gallery.3":{"url":"https://s3.amazonaws.com/redqteam.com/pickbazar/gucci_mini_purse.jpg","__typename":"Gallery"},"Product:50":{"id":50,"title":"Hp Laptop Bag","slug":"hp-laptop-bag","unit":"1 pc(s)","price":295,"salePrice":236,"description":"Bewitching black, plush padding and faux-fur lining surround and cradle your 15.6 Ultrabook in trendsetting luxury. It is the perfect accessory for every season and all occasions. Dress it up; dress it down. Take it with you everywhere you go.","discountInPercent":20,"type":"BAGS","image":"https://s3.amazonaws.com/redqteam.com/pickbazar/hp_laptop_bag.jpg","author":null,"gallery":[{"type":"id","generated":true,"id":"Product:50.gallery.0","typename":"Gallery"},{"type":"id","generated":true,"id":"Product:50.gallery.1","typename":"Gallery"},{"type":"id","generated":true,"id":"Product:50.gallery.2","typename":"Gallery"},{"type":"id","generated":true,"id":"Product:50.gallery.3","typename":"Gallery"}],"categories":[{"type":"id","generated":false,"id":"Category:18","typename":"Category"}],"__typename":"Product"},"Product:50.gallery.0":{"url":"https://s3.amazonaws.com/redqteam.com/pickbazar/hp_laptop_bag.jpg","__typename":"Gallery"},"Product:50.gallery.1":{"url":"https://s3.amazonaws.com/redqteam.com/pickbazar/hp_laptop_bag.jpg","__typename":"Gallery"},"Product:50.gallery.2":{"url":"https://s3.amazonaws.com/redqteam.com/pickbazar/hp_laptop_bag.jpg","__typename":"Gallery"},"Product:50.gallery.3":{"url":"https://s3.amazonaws.com/redqteam.com/pickbazar/hp_laptop_bag.jpg","__typename":"Gallery"},"Product:51":{"id":51,"title":"Mac Laptop Bag","slug":"mac-laptop-bag","unit":"1 pc(s)","price":325,"salePrice":0,"description":"Bewitching black, plush padding and faux-fur lining surround and cradle your 15.6 macbook™ in trendsetting luxury. It is the perfect accessory for every season and all occasions. Dress it up; dress it down. Take it with you everywhere you go.","discountInPercent":0,"type":"BAGS","image":"https://s3.amazonaws.com/redqteam.com/pickbazar/mac_laptop_bag.jpg","author":null,"gallery":[{"type":"id","generated":true,"id":"Product:51.gallery.0","typename":"Gallery"},{"type":"id","generated":true,"id":"Product:51.gallery.1","typename":"Gallery"},{"type":"id","generated":true,"id":"Product:51.gallery.2","typename":"Gallery"},{"type":"id","generated":true,"id":"Product:51.gallery.3","typename":"Gallery"}],"categories":[{"type":"id","generated":false,"id":"Category:18","typename":"Category"}],"__typename":"Product"},"Product:51.gallery.0":{"url":"https://s3.amazonaws.com/redqteam.com/pickbazar/mac_laptop_bag.jpg","__typename":"Gallery"},"Product:51.gallery.1":{"url":"https://s3.amazonaws.com/redqteam.com/pickbazar/mac_laptop_bag.jpg","__typename":"Gallery"},"Product:51.gallery.2":{"url":"https://s3.amazonaws.com/redqteam.com/pickbazar/mac_laptop_bag.jpg","__typename":"Gallery"},"Product:51.gallery.3":{"url":"https://s3.amazonaws.com/redqteam.com/pickbazar/mac_laptop_bag.jpg","__typename":"Gallery"},"Product:52":{"id":52,"title":"Muse Wallet","slug":"muse-wallet","unit":"1 pc(s)","price":80,"salePrice":0,"description":"Muse Medium Zip Around Wallet has been crafted from a beautiful clotted cream saffiano leather. The leather has been thoughtfully paired with brass hardware throughout and a discrete foil logo. The interior is lined with cotton twill and is fitted with 2 main compartments with a zip coin pocket, 2 note pockets and 12 credit card slots, all in soft nappa leather.","discountInPercent":0,"type":"BAGS","image":"https://s3.amazonaws.com/redqteam.com/pickbazar/Muse_wallet.jpg","author":null,"gallery":[{"type":"id","generated":true,"id":"Product:52.gallery.0","typename":"Gallery"},{"type":"id","generated":true,"id":"Product:52.gallery.1","typename":"Gallery"},{"type":"id","generated":true,"id":"Product:52.gallery.2","typename":"Gallery"},{"type":"id","generated":true,"id":"Product:52.gallery.3","typename":"Gallery"}],"categories":[{"type":"id","generated":false,"id":"Category:17","typename":"Category"}],"__typename":"Product"},"Product:52.gallery.0":{"url":"https://s3.amazonaws.com/redqteam.com/pickbazar/Muse_wallet.jpg","__typename":"Gallery"},"Product:52.gallery.1":{"url":"https://s3.amazonaws.com/redqteam.com/pickbazar/Muse_wallet.jpg","__typename":"Gallery"},"Product:52.gallery.2":{"url":"https://s3.amazonaws.com/redqteam.com/pickbazar/Muse_wallet.jpg","__typename":"Gallery"},"Product:52.gallery.3":{"url":"https://s3.amazonaws.com/redqteam.com/pickbazar/Muse_wallet.jpg","__typename":"Gallery"},"Product:53":{"id":53,"title":"Philip Lim Shoulder Bag","slug":"philip-lim-shoulder-bag","unit":"1 pc(s)","price":250,"salePrice":0,"description":"Structured buffed nappa leather top handle bag in 'scarlet' red. Carry handle at top. Detachable and adjustable shoulder strap with lanyard clasp fastening. Foldover flap with signature logo-engraved 'paper clip' fastening. Patch pocket and gold-tone logo stamp at two-compartment interior. ","discountInPercent":0,"type":"BAGS","image":"https://s3.amazonaws.com/redqteam.com/pickbazar/Philip_lim_shoulder_bag.jpg","author":null,"gallery":[{"type":"id","generated":true,"id":"Product:53.gallery.0","typename":"Gallery"},{"type":"id","generated":true,"id":"Product:53.gallery.1","typename":"Gallery"},{"type":"id","generated":true,"id":"Product:53.gallery.2","typename":"Gallery"},{"type":"id","generated":true,"id":"Product:53.gallery.3","typename":"Gallery"}],"categories":[{"type":"id","generated":false,"id":"Category:16","typename":"Category"}],"__typename":"Product"},"Product:53.gallery.0":{"url":"https://s3.amazonaws.com/redqteam.com/pickbazar/Philip_lim_shoulder_bag.jpg","__typename":"Gallery"},"Product:53.gallery.1":{"url":"https://s3.amazonaws.com/redqteam.com/pickbazar/Philip_lim_shoulder_bag.jpg","__typename":"Gallery"},"Product:53.gallery.2":{"url":"https://s3.amazonaws.com/redqteam.com/pickbazar/Philip_lim_shoulder_bag.jpg","__typename":"Gallery"},"Product:53.gallery.3":{"url":"https://s3.amazonaws.com/redqteam.com/pickbazar/Philip_lim_shoulder_bag.jpg","__typename":"Gallery"},"Product:54":{"id":54,"title":"Sports Shoulder Bag","slug":"sports-shoulder-bag","unit":"1 pc(s)","price":150,"salePrice":0,"description":"Structured buffed nappa leather top handle bag in 'scarlet' red. Carry handle at top. Detachable and adjustable shoulder strap with lanyard clasp fastening. Foldover flap with signature logo-engraved 'paper clip' fastening. Patch pocket and gold-tone logo stamp at two-compartment interior. ","discountInPercent":0,"type":"BAGS","image":"https://s3.amazonaws.com/redqteam.com/pickbazar/Sports_shoulder_bag.jpg","author":null,"gallery":[{"type":"id","generated":true,"id":"Product:54.gallery.0","typename":"Gallery"},{"type":"id","generated":true,"id":"Product:54.gallery.1","typename":"Gallery"},{"type":"id","generated":true,"id":"Product:54.gallery.2","typename":"Gallery"},{"type":"id","generated":true,"id":"Product:54.gallery.3","typename":"Gallery"}],"categories":[{"type":"id","generated":false,"id":"Category:16","typename":"Category"}],"__typename":"Product"},"Product:54.gallery.0":{"url":"https://s3.amazonaws.com/redqteam.com/pickbazar/Sports_shoulder_bag.jpg","__typename":"Gallery"},"Product:54.gallery.1":{"url":"https://s3.amazonaws.com/redqteam.com/pickbazar/Sports_shoulder_bag.jpg","__typename":"Gallery"},"Product:54.gallery.2":{"url":"https://s3.amazonaws.com/redqteam.com/pickbazar/Sports_shoulder_bag.jpg","__typename":"Gallery"},"Product:54.gallery.3":{"url":"https://s3.amazonaws.com/redqteam.com/pickbazar/Sports_shoulder_bag.jpg","__typename":"Gallery"},"$ROOT_QUERY.products({\"limit\":20,\"offset\":0,\"type\":\"bags\"})":{"items":[{"type":"id","generated":false,"id":"Product:35","typename":"Product"},{"type":"id","generated":false,"id":"Product:36","typename":"Product"},{"type":"id","generated":false,"id":"Product:37","typename":"Product"},{"type":"id","generated":false,"id":"Product:38","typename":"Product"},{"type":"id","generated":false,"id":"Product:39","typename":"Product"},{"type":"id","generated":false,"id":"Product:40","typename":"Product"},{"type":"id","generated":false,"id":"Product:41","typename":"Product"},{"type":"id","generated":false,"id":"Product:42","typename":"Product"},{"type":"id","generated":false,"id":"Product:43","typename":"Product"},{"type":"id","generated":false,"id":"Product:44","typename":"Product"},{"type":"id","generated":false,"id":"Product:45","typename":"Product"},{"type":"id","generated":false,"id":"Product:46","typename":"Product"},{"type":"id","generated":false,"id":"Product:47","typename":"Product"},{"type":"id","generated":false,"id":"Product:48","typename":"Product"},{"type":"id","generated":false,"id":"Product:49","typename":"Product"},{"type":"id","generated":false,"id":"Product:50","typename":"Product"},{"type":"id","generated":false,"id":"Product:51","typename":"Product"},{"type":"id","generated":false,"id":"Product:52","typename":"Product"},{"type":"id","generated":false,"id":"Product:53","typename":"Product"},{"type":"id","generated":false,"id":"Product:54","typename":"Product"}],"hasMore":true,"__typename":"ProductResponse"},"ROOT_QUERY":{"products({\"limit\":20,\"offset\":0,\"type\":\"bags\"})":{"type":"id","generated":true,"id":"$ROOT_QUERY.products({\"limit\":20,\"offset\":0,\"type\":\"bags\"})","typename":"ProductResponse"},"categories({\"type\":\"bags\"})":[{"type":"id","generated":false,"id":"Category:14","typename":"Category"},{"type":"id","generated":false,"id":"Category:15","typename":"Category"},{"type":"id","generated":false,"id":"Category:16","typename":"Category"},{"type":"id","generated":false,"id":"Category:17","typename":"Category"},{"type":"id","generated":false,"id":"Category:18","typename":"Category"}]}}},"__N_SSG":true}